MANIFEST.in
README.md
setup.py
IXDjango.egg-info/PKG-INFO
IXDjango.egg-info/SOURCES.txt
IXDjango.egg-info/dependency_links.txt
IXDjango.egg-info/requires.txt
IXDjango.egg-info/top_level.txt
ixdjango/__init__.py
ixdjango/docker_settings.py
ixdjango/logging_.py
ixdjango/models.py
ixdjango/utils.py
ixdjango/management/__init__.py
ixdjango/management/commands/__init__.py
ixdjango/management/commands/clear_app.py
ixdjango/management/commands/copystatic.py
ixdjango/management/commands/deploy.py
ixdjango/management/commands/loadixfixtures.py
ixdjango/management/commands/newrelic_notify_deploy.py
ixdjango/test_suite/__init__.py
ixdjango/test_suite/utils.py
ixdjango/tests/__init__.py