Metadata-Version: 1.0
Name: IXDjango
Version: 1.0.3
Summary: Management commands for deploying Django projects.
Home-page: http://pypi.python.org/pypi/IXDjango/
Author: Infoxchange Australia dev team
Author-email: devs@infoxchange.net.au
License: MIT
Platform: UNKNOWN
